anteater/__init__.py
anteater/anteater.py
anteater/ANTS/__init__.py
Anteater_Recon-1.0.0.dist-info/LICENSE
Anteater_Recon-1.0.0.dist-info/METADATA
Anteater_Recon-1.0.0.dist-info/WHEEL
Anteater_Recon-1.0.0.dist-info/top_level.txt
Anteater_Recon-1.0.0.dist-info/RECORD
